bertopic/__init__.py
bertopic/_bertopic.py
bertopic/_save_utils.py
bertopic/_utils.py
bertopic/backend/__init__.py
bertopic/backend/_base.py
bertopic/backend/_cohere.py
bertopic/backend/_fastembed.py
bertopic/backend/_flair.py
bertopic/backend/_gensim.py
bertopic/backend/_hftransformers.py
bertopic/backend/_langchain.py
bertopic/backend/_model2vec.py
bertopic/backend/_multimodal.py
bertopic/backend/_openai.py
bertopic/backend/_sentencetransformers.py
bertopic/backend/_sklearn.py
bertopic/backend/_spacy.py
bertopic/backend/_use.py
bertopic/backend/_utils.py
bertopic/backend/_word_doc.py
bertopic/cluster/__init__.py
bertopic/cluster/_base.py
bertopic/cluster/_utils.py
bertopic/dimensionality/__init__.py
bertopic/dimensionality/_base.py
bertopic/plotting/__init__.py
bertopic/plotting/_approximate_distribution.py
bertopic/plotting/_barchart.py
bertopic/plotting/_datamap.py
bertopic/plotting/_distribution.py
bertopic/plotting/_documents.py
bertopic/plotting/_heatmap.py
bertopic/plotting/_hierarchical_documents.py
bertopic/plotting/_hierarchy.py
bertopic/plotting/_term_rank.py
bertopic/plotting/_topics.py
bertopic/plotting/_topics_over_time.py
bertopic/plotting/_topics_per_class.py
bertopic/representation/__init__.py
bertopic/representation/_base.py
bertopic/representation/_cohere.py
bertopic/representation/_keybert.py
bertopic/representation/_langchain.py
bertopic/representation/_litellm.py
bertopic/representation/_llamacpp.py
bertopic/representation/_mmr.py
bertopic/representation/_openai.py
bertopic/representation/_pos.py
bertopic/representation/_textgeneration.py
bertopic/representation/_utils.py
bertopic/representation/_visual.py
bertopic/representation/_zeroshot.py
bertopic/vectorizers/__init__.py
bertopic/vectorizers/_ctfidf.py
bertopic/vectorizers/_online_cv.py
bertopic-0.17.4.dist-info/licenses/LICENSE
bertopic-0.17.4.dist-info/METADATA
bertopic-0.17.4.dist-info/WHEEL
bertopic-0.17.4.dist-info/top_level.txt
bertopic-0.17.4.dist-info/RECORD
