Metadata-Version: 2.4
Name: bertopic
Version: 0.17.4
Summary: BERTopic performs topic Modeling with state-of-the-art transformer models.
Author-email: "Maarten P. Grootendorst" <maartengrootendorst@gmail.com>
License: MIT License
Project-URL: Documentation, https://maartengr.github.io/BERTopic/
Project-URL: Homepage, https://github.com/MaartenGr/BERTopic
Project-URL: Issues, https://github.com/MaartenGr/BERTopic/issues
Project-URL: Repository, https://github.com/MaartenGr/BERTopic.git
Keywords: nlp,bert,topic,modeling,embeddings
Classifier: Intended Audience :: Developers
Classifier: Intended Audience :: Science/Research
Classifier: License :: OSI Approved :: MIT License
Classifier: Operating System :: MacOS
Classifier: Operating System :: Microsoft :: Windows
Classifier: Operating System :: POSIX
Classifier: Operating System :: Unix
Classifier: Programming Language :: Python
Classifier: Programming Language :: Python :: 3.10
Classifier: Programming Language :: Python :: 3.11
Classifier: Programming Language :: Python :: 3.12
Classifier: Programming Language :: Python :: 3.13
Classifier: Topic :: Scientific/Engineering
Classifier: Topic :: Scientific/Engineering :: Artificial Intelligence
Requires-Python: >=3.10
License-File: LICENSE
Requires-Dist: hdbscan>=0.8.29
Requires-Dist: umap-learn>=0.5.0
Requires-Dist: numpy>=1.20.0
Requires-Dist: pandas>=1.1.5
Requires-Dist: plotly>=4.7.0
Requires-Dist: scikit-learn>=1.0
Requires-Dist: sentence-transformers>=0.4.1
Requires-Dist: tqdm>=4.41.1
Requires-Dist: llvmlite>0.36.0
Provides-Extra: datamap
Requires-Dist: datamapplot>=0.1; extra == "datamap"
Requires-Dist: matplotlib>=3.8; extra == "datamap"
Provides-Extra: dev
Requires-Dist: bertopic[docs,test]; extra == "dev"
Provides-Extra: docs
Requires-Dist: mkdocs==1.5.3; extra == "docs"
Requires-Dist: mkdocs-material==9.5.18; extra == "docs"
Requires-Dist: mkdocstrings-python==1.10.0; extra == "docs"
Requires-Dist: mkdocstrings==0.24.3; extra == "docs"
Provides-Extra: fastembed
Requires-Dist: fastembed>=0.6.0; extra == "fastembed"
Provides-Extra: flair
Requires-Dist: flair>=0.7; extra == "flair"
Requires-Dist: torch>=1.4.0; extra == "flair"
Requires-Dist: transformers>=3.5.1; extra == "flair"
Provides-Extra: gensim
Requires-Dist: gensim>=4.0.0; extra == "gensim"
Provides-Extra: spacy
Requires-Dist: spacy>=3.0.1; extra == "spacy"
Provides-Extra: test
Requires-Dist: pytest>=5.4.3; extra == "test"
Requires-Dist: pytest-cov>=2.6.1; extra == "test"
Requires-Dist: ruff~=0.14.0; extra == "test"
Provides-Extra: use
Requires-Dist: tensorflow; extra == "use"
Requires-Dist: tensorflow_hub; extra == "use"
Requires-Dist: tensorflow_text; extra == "use"
Provides-Extra: vision
Requires-Dist: accelerate>=0.19.0; extra == "vision"
Requires-Dist: Pillow>=9.2.0; extra == "vision"
Dynamic: license-file
